{
    "instance": {
        "name": "Alexander - The Breath of the Creator (Savage)",
        "category": "Raids",
        "description": "None can deny the wandering minstrel's inimitable way with words, nor the manner in which his penchant for embellishment and exaggeration has rendered your triumph over the primal Alexander all the more triumphant─and the insurmountable odds over which you did prevail all the more insurmountable. Reach back into your memory and relive your adventure inside the steel giant as it will live on in the hearts and minds of all who hear the tale!",
        "id": 30044,
        "patch": 3.4,
        "categoryIcon": 61802,
        "time": 90,
        "min_lvl": 60,
        "fullIcon": 112193,
        "healer": 2,
        "tank": 2,
        "ranged": 2,
        "melee": 2,
        "max_lvl": 60,
        "min_ilvl": 250,
        "fights": [
            {
                "currency": [
                    {
                        "id": 28,
                        "amount": 30
                    }
                ],
                "type": "Boss",
                "coffer": {
                    "items": [
                        16503,
                        16505,
                        16499,
                        16511,
                        16495,
                        16501,
                        16513,
                        16479,
                        16491,
                        16487,
                        16517,
                        16483,
                        16489,
                        16519,
                        16541,
                        16542
                    ]
                },
                "mobs": [
                    61150000005180
                ]
            }
        ],
        "rewards": [
            16554
        ],
        "currency": [
            {
                "id": 28,
                "amount": 30
            }
        ]
    },
    "partials": [
        {
            "type": "item",
            "id": "16503",
            "obj": {
                "i": 16503,
                "n": "Alexandrian Mask of Scouting",
                "l": 270,
                "c": 40490,
                "t": 34
            }
        },
        {
            "type": "item",
            "id": "16505",
            "obj": {
                "i": 16505,
                "n": "Alexandrian Gloves of Scouting",
                "l": 270,
                "c": 44476,
                "t": 37
            }
        },
        {
            "type": "item",
            "id": "16499",
            "obj": {
                "i": 16499,
                "n": "Alexandrian Gloves of Aiming",
                "l": 270,
                "c": 44474,
                "t": 37
            }
        },
        {
            "type": "item",
            "id": "16511",
            "obj": {
                "i": 16511,
                "n": "Alexandrian Gloves of Healing",
                "l": 270,
                "c": 44478,
                "t": 37
            }
        },
        {
            "type": "item",
            "id": "16495",
            "obj": {
                "i": 16495,
                "n": "Alexandrian Thighboots of Striking",
                "l": 270,
                "c": 46645,
                "t": 38
            }
        },
        {
            "type": "item",
            "id": "16501",
            "obj": {
                "i": 16501,
                "n": "Alexandrian Thighboots of Aiming",
                "l": 270,
                "c": 46647,
                "t": 38
            }
        },
        {
            "type": "item",
            "id": "16513",
            "obj": {
                "i": 16513,
                "n": "Alexandrian Boots of Healing",
                "l": 270,
                "c": 46651,
                "t": 38
            }
        },
        {
            "type": "item",
            "id": "16479",
            "obj": {
                "i": 16479,
                "n": "Alexandrian Visor of Fending",
                "l": 270,
                "c": 40484,
                "t": 34
            }
        },
        {
            "type": "item",
            "id": "16491",
            "obj": {
                "i": 16491,
                "n": "Alexandrian Mask of Striking",
                "l": 270,
                "c": 40488,
                "t": 34
            }
        },
        {
            "type": "item",
            "id": "16487",
            "obj": {
                "i": 16487,
                "n": "Alexandrian Gauntlets of Maiming",
                "l": 270,
                "c": 48562,
                "t": 37
            }
        },
        {
            "type": "item",
            "id": "16517",
            "obj": {
                "i": 16517,
                "n": "Alexandrian Gloves of Casting",
                "l": 270,
                "c": 44480,
                "t": 37
            }
        },
        {
            "type": "item",
            "id": "16483",
            "obj": {
                "i": 16483,
                "n": "Alexandrian Sollerets of Fending",
                "l": 270,
                "c": 46641,
                "t": 38
            }
        },
        {
            "type": "item",
            "id": "16489",
            "obj": {
                "i": 16489,
                "n": "Alexandrian Sollerets of Maiming",
                "l": 270,
                "c": 46643,
                "t": 38
            }
        },
        {
            "type": "item",
            "id": "16519",
            "obj": {
                "i": 16519,
                "n": "Alexandrian Boots of Casting",
                "l": 270,
                "c": 46653,
                "t": 38
            }
        },
        {
            "type": "item",
            "id": "16541",
            "obj": {
                "i": 16541,
                "n": "Micro Tomestone",
                "l": 1,
                "c": 25994,
                "t": 63
            }
        },
        {
            "type": "item",
            "id": "16542",
            "obj": {
                "i": 16542,
                "n": "Illuminati Darkest Gobcoat",
                "l": 1,
                "c": 20684,
                "t": 63
            }
        },
        {
            "type": "mob",
            "id": "61150000005180",
            "obj": {
                "i": 61150000005180,
                "n": "Lamebrix Strikebocks",
                "l": "60",
                "z": 1841,
                "t": "Alexander - The Breath of the Creator (Savage)"
            }
        },
        {
            "type": "item",
            "id": "16554",
            "obj": {
                "i": 16554,
                "n": "Alexandrian Manifesto - Page 2",
                "l": 1,
                "c": 26427,
                "t": 61
            }
        }
    ]
}