{
    "instance": {
        "name": "The Aitiascope",
        "category": "Dungeons",
        "description": "Deep in the heart of Labyrinthos lies its secret among secrets─the device through which the Sharlayans have peered into the aetherial sea to learn Hydaelyn's secrets. With their bargain with the Forum fulfilled, the Scions of the Seventh Dawn are poised to journey to the Aitiascope and beyond to beg Her aid, but no depths are without their darkness...",
        "id": 81,
        "patch": 6.0,
        "categoryIcon": 61801,
        "time": 90,
        "min_lvl": 89,
        "fullIcon": 112439,
        "healer": 1,
        "tank": 1,
        "ranged": 1,
        "melee": 1,
        "max_lvl": 90,
        "min_ilvl": 520,
        "max_ilvl": 550,
        "fights": [
            {
                "type": "MidBoss",
                "coffer": {
                    "items": [
                        34810,
                        34811,
                        34812,
                        34814,
                        34813,
                        34815,
                        34816,
                        34817,
                        34819,
                        34818
                    ]
                }
            },
            {
                "type": "MidBoss",
                "coffer": {
                    "items": [
                        34820,
                        34821,
                        34822,
                        34824,
                        34823,
                        34825,
                        34826,
                        34827,
                        34829,
                        34828,
                        33919,
                        33920,
                        33918,
                        33928,
                        33929,
                        33921,
                        33917
                    ]
                }
            },
            {
                "type": "Boss",
                "coffer": {
                    "items": [
                        34810,
                        34811,
                        34812,
                        34814,
                        34813,
                        34815,
                        34816,
                        34817,
                        34819,
                        34818,
                        35982,
                        36351
                    ]
                }
            }
        ],
        "coffers": [
            {
                "items": [
                    33919,
                    33920,
                    33918,
                    33928,
                    33929,
                    33921,
                    33917
                ],
                "coords": [
                    "11.8",
                    "12.6"
                ]
            },
            {
                "items": [
                    34820,
                    34821,
                    34822,
                    34824,
                    34823,
                    34825,
                    34826,
                    34827,
                    34829,
                    34828
                ],
                "coords": [
                    "11.3",
                    "10.0"
                ]
            },
            {
                "items": [
                    34810,
                    34811,
                    34812,
                    34814,
                    34813,
                    34815,
                    34816,
                    34817,
                    34819,
                    34818,
                    33919,
                    33920,
                    33918,
                    33928,
                    33929,
                    33921,
                    33917
                ],
                "coords": [
                    "11.2",
                    "13.1"
                ]
            },
            {
                "items": [
                    34820,
                    34821,
                    34822,
                    34824,
                    34823,
                    34825,
                    34826,
                    34827,
                    34829,
                    34828,
                    33919,
                    33920,
                    33918,
                    33928,
                    33929,
                    33921,
                    33917
                ],
                "coords": [
                    "11.2",
                    "8.9"
                ]
            }
        ],
        "rewards": [
            36272
        ],
        "unlockedByQuest": 69985
    },
    "partials": [
        {
            "type": "item",
            "id": "34810",
            "obj": {
                "i": 34810,
                "n": "Etheirys Earring of Fending",
                "l": 548,
                "c": 55485,
                "t": 41
            }
        },
        {
            "type": "item",
            "id": "34811",
            "obj": {
                "i": 34811,
                "n": "Etheirys Earring of Slaying",
                "l": 548,
                "c": 55485,
                "t": 41
            }
        },
        {
            "type": "item",
            "id": "34812",
            "obj": {
                "i": 34812,
                "n": "Etheirys Earring of Aiming",
                "l": 548,
                "c": 55485,
                "t": 41
            }
        },
        {
            "type": "item",
            "id": "34814",
            "obj": {
                "i": 34814,
                "n": "Etheirys Earring of Casting",
                "l": 548,
                "c": 55485,
                "t": 41
            }
        },
        {
            "type": "item",
            "id": "34813",
            "obj": {
                "i": 34813,
                "n": "Etheirys Earring of Healing",
                "l": 548,
                "c": 55485,
                "t": 41
            }
        },
        {
            "type": "item",
            "id": "34815",
            "obj": {
                "i": 34815,
                "n": "Etheirys Choker of Fending",
                "l": 548,
                "c": 55048,
                "t": 40
            }
        },
        {
            "type": "item",
            "id": "34816",
            "obj": {
                "i": 34816,
                "n": "Etheirys Choker of Slaying",
                "l": 548,
                "c": 55048,
                "t": 40
            }
        },
        {
            "type": "item",
            "id": "34817",
            "obj": {
                "i": 34817,
                "n": "Etheirys Choker of Aiming",
                "l": 548,
                "c": 55048,
                "t": 40
            }
        },
        {
            "type": "item",
            "id": "34819",
            "obj": {
                "i": 34819,
                "n": "Etheirys Choker of Casting",
                "l": 548,
                "c": 55048,
                "t": 40
            }
        },
        {
            "type": "item",
            "id": "34818",
            "obj": {
                "i": 34818,
                "n": "Etheirys Choker of Healing",
                "l": 548,
                "c": 55048,
                "t": 40
            }
        },
        {
            "type": "item",
            "id": "34820",
            "obj": {
                "i": 34820,
                "n": "Etheirys Bracelet of Fending",
                "l": 548,
                "c": 55850,
                "t": 42
            }
        },
        {
            "type": "item",
            "id": "34821",
            "obj": {
                "i": 34821,
                "n": "Etheirys Bracelet of Slaying",
                "l": 548,
                "c": 55850,
                "t": 42
            }
        },
        {
            "type": "item",
            "id": "34822",
            "obj": {
                "i": 34822,
                "n": "Etheirys Bracelet of Aiming",
                "l": 548,
                "c": 55850,
                "t": 42
            }
        },
        {
            "type": "item",
            "id": "34824",
            "obj": {
                "i": 34824,
                "n": "Etheirys Bracelet of Casting",
                "l": 548,
                "c": 55850,
                "t": 42
            }
        },
        {
            "type": "item",
            "id": "34823",
            "obj": {
                "i": 34823,
                "n": "Etheirys Bracelet of Healing",
                "l": 548,
                "c": 55850,
                "t": 42
            }
        },
        {
            "type": "item",
            "id": "34825",
            "obj": {
                "i": 34825,
                "n": "Etheirys Ring of Fending",
                "l": 548,
                "c": 54701,
                "t": 43
            }
        },
        {
            "type": "item",
            "id": "34826",
            "obj": {
                "i": 34826,
                "n": "Etheirys Ring of Slaying",
                "l": 548,
                "c": 54701,
                "t": 43
            }
        },
        {
            "type": "item",
            "id": "34827",
            "obj": {
                "i": 34827,
                "n": "Etheirys Ring of Aiming",
                "l": 548,
                "c": 54701,
                "t": 43
            }
        },
        {
            "type": "item",
            "id": "34829",
            "obj": {
                "i": 34829,
                "n": "Etheirys Ring of Casting",
                "l": 548,
                "c": 54701,
                "t": 43
            }
        },
        {
            "type": "item",
            "id": "34828",
            "obj": {
                "i": 34828,
                "n": "Etheirys Ring of Healing",
                "l": 548,
                "c": 54701,
                "t": 43
            }
        },
        {
            "type": "item",
            "id": "33919",
            "obj": {
                "i": 33919,
                "n": "Savage Aim Materia IX",
                "l": 560,
                "c": 20284,
                "t": 58,
                "materia": {
                    "tier": 8,
                    "value": 12,
                    "attr": "Critical Hit",
                    "category": 0
                }
            }
        },
        {
            "type": "item",
            "id": "33920",
            "obj": {
                "i": 33920,
                "n": "Savage Might Materia IX",
                "l": 560,
                "c": 20284,
                "t": 58,
                "materia": {
                    "tier": 8,
                    "value": 12,
                    "attr": "Determination",
                    "category": 0
                }
            }
        },
        {
            "type": "item",
            "id": "33918",
            "obj": {
                "i": 33918,
                "n": "Heavens' Eye Materia IX",
                "l": 560,
                "c": 20284,
                "t": 58,
                "materia": {
                    "tier": 8,
                    "value": 12,
                    "attr": "Direct Hit Rate",
                    "category": 0
                }
            }
        },
        {
            "type": "item",
            "id": "33928",
            "obj": {
                "i": 33928,
                "n": "Quickarm Materia IX",
                "l": 560,
                "c": 20282,
                "t": 58,
                "materia": {
                    "tier": 8,
                    "value": 12,
                    "attr": "Skill Speed",
                    "category": 0
                }
            }
        },
        {
            "type": "item",
            "id": "33929",
            "obj": {
                "i": 33929,
                "n": "Quicktongue Materia IX",
                "l": 560,
                "c": 20282,
                "t": 58,
                "materia": {
                    "tier": 8,
                    "value": 12,
                    "attr": "Spell Speed",
                    "category": 0
                }
            }
        },
        {
            "type": "item",
            "id": "33921",
            "obj": {
                "i": 33921,
                "n": "Battledance Materia IX",
                "l": 560,
                "c": 20281,
                "t": 58,
                "materia": {
                    "tier": 8,
                    "value": 12,
                    "attr": "Tenacity",
                    "category": 0
                }
            }
        },
        {
            "type": "item",
            "id": "33917",
            "obj": {
                "i": 33917,
                "n": "Piety Materia IX",
                "l": 560,
                "c": 20281,
                "t": 58,
                "materia": {
                    "tier": 8,
                    "value": 12,
                    "attr": "Piety",
                    "category": 0,
                    "advancedMeldingForbidden": 1
                }
            }
        },
        {
            "type": "item",
            "id": "35982",
            "obj": {
                "i": 35982,
                "n": "Tiny Troll",
                "l": 1,
                "c": 59834,
                "t": 81
            }
        },
        {
            "type": "item",
            "id": "36351",
            "obj": {
                "i": 36351,
                "n": "The Aetherial Sea Orchestrion Roll",
                "l": 1,
                "c": 25945,
                "t": 94
            }
        },
        {
            "type": "item",
            "id": "36272",
            "obj": {
                "i": 36272,
                "n": "Amon the Undying Card",
                "l": 1,
                "c": 27664,
                "t": 86
            }
        },
        {
            "type": "quest",
            "id": "69985",
            "obj": {
                "i": 69985,
                "n": "Her Children, One and All",
                "g": 11,
                "l": "Labyrinthos",
                "s": 603
            }
        }
    ]
}